tkinterclock01/__init__.py
TkinterClock01-1.0.3.dist-info/LICENSE.txt
TkinterClock01-1.0.3.dist-info/METADATA
TkinterClock01-1.0.3.dist-info/WHEEL
TkinterClock01-1.0.3.dist-info/top_level.txt
TkinterClock01-1.0.3.dist-info/RECORD
