Metadata-Version: 2.1
Name: TkinterClock01
Version: 1.0.3
Summary: A tkinter based window clock, dipslays time, date, and clock name.
Home-page: https://github.com/GrandMoff100/TkinterClock01
Author: Quantum_Wizard
Author-email: minecraftcrusher100@gmail.com
License: UNKNOWN
Platform: UNKNOWN
Classifier: Programming Language :: Python :: 3
Classifier: License :: OSI Approved :: MIT License
Requires-Python: >=3.7
Requires-Dist: omegamath01
